aedttest/__init__.py
aedttest/aedt_test_runner.py
aedttest/logger.py
aedttest/logger.pyi
aedttest/py.typed
aedttest/simulation_data.py
aedttest/simulation_data.pyi
aedttest/clusters/__init__.py
aedttest/clusters/job_hosts.py
aedttest/clusters/job_hosts.pyi
aedttest/static/css/style.css
aedttest/static/css/css-lib/bootstrap-slider.css
aedttest/static/css/css-lib/bootstrap.min.css
aedttest/static/css/css-lib/jquery-ui.min.css
aedttest/static/js/chartjs-init.js
aedttest/static/js/common.js
aedttest/static/js/main.js
aedttest/static/js/project.js
aedttest/static/js/js-lib/Chart.bundle.js
aedttest/static/js/js-lib/bootstrap-slider.min.js
aedttest/static/js/js-lib/bootstrap.min.js
aedttest/static/js/js-lib/jquery.min.js
aedttest/static/js/js-lib/jquery.nanoscroller.min.js
aedttest/static/templates/main.html
aedttest/static/templates/project-report.html
aedttest-0.0.2.dist-info/entry_points.txt
aedttest-0.0.2.dist-info/LICENSE
aedttest-0.0.2.dist-info/WHEEL
aedttest-0.0.2.dist-info/METADATA
aedttest-0.0.2.dist-info/RECORD
