Metadata-Version: 2.1
Name: aedttest
Version: 0.0.2
Summary: Ansys Electronics Desktop Testing Framework.
Author-email: Maksim Beliaev <maksim.beliaev@ansys.com>, Bo Yang <bo.yang@ansys.com>, Samuel Lopez <samuel.lopez@ansys.com>
Requires-Python: >=3.7
Classifier: License :: OSI Approved :: MIT License
Classifier: Operating System :: OS Independent
Classifier: Programming Language :: Python :: 3
Classifier: Programming Language :: Python :: 3.7
Classifier: Programming Language :: Python :: 3.8
Classifier: Programming Language :: Python :: 3.9
Classifier: Programming Language :: Python :: 3.10
Requires-Dist: pyaedt==0.6.57
Requires-Dist: Django==3.2.18
Requires-Dist: tomli>=2.0.0
Requires-Dist: flit==3.4.0 ; extra == "deploy"
Requires-Dist: pre-commit==2.15.0 ; extra == "test"
Requires-Dist: mypy==0.960 ; extra == "test"
Requires-Dist: pytest==6.2.5 ; extra == "test"
Requires-Dist: pytest-cov==3.0.0 ; extra == "test"
Requires-Dist: webdriver-manager ; extra == "test"
Requires-Dist: selenium>4 ; extra == "test"
Project-URL: Home, https://github.com/ansys/aedt-testing
Provides-Extra: deploy
Provides-Extra: test
